turingdb-1.20.0.dist-info/RECORD
turingdb-1.20.0.dist-info/WHEEL
turingdb-1.20.0.dist-info/entry_points.txt
turingdb-1.20.0.dist-info/top_level.txt
turingdb-1.20.0.dist-info/METADATA
turingdb-1.20.0.dist-info/licenses/LICENSE
turingdb/turingdb.py
turingdb/_version.py
turingdb/protocol.py
turingdb/__init__.py
turingdb/exceptions.py
turingdb/s3.py
turingdb/path.py
turingdb/bin/turingdb
turingdb/.dylibs/libc++abi.1.0.dylib
turingdb/.dylibs/libunwind.1.0.dylib
turingdb/.dylibs/libc++.1.0.dylib
turingdb/.dylibs/libomp.dylib
