Metadata-Version: 2.4
Name: turingdb
Version: 1.20.0
Project-URL: Homepage, https://github.com/turing-db/turingdb
Project-URL: Repository, https://github.com/turing-db/turingdb
Requires-Python: >=3.10
License-File: LICENSE
Requires-Dist: boto3>=1.42.22
Requires-Dist: boto3-stubs>=1.42.22
Requires-Dist: click>=8.3.1
Requires-Dist: httpx>=0.28.1
Requires-Dist: orjson>=3.11.5
Requires-Dist: pandas>=2.3.3
Requires-Dist: pandas-stubs>=2.3.3.251219
Requires-Dist: prompt-toolkit>=3.0.52
Requires-Dist: patchelf>=0.17.2.4
Dynamic: license-file
Dynamic: requires-python
